turtlelab/__init__.py
turtlelab/__main__.py
turtlelab/core.py
turtlelab/examples/spiral.py
turtlelab/examples/square.py
turtlelab/examples/star.py
turtlelab-0.1.0.dist-info/WHEEL
turtlelab-0.1.0.dist-info/entry_points.txt
turtlelab-0.1.0.dist-info/METADATA
turtlelab-0.1.0.dist-info/RECORD
