Metadata-Version: 2.4
Name: turtlelab
Version: 0.1.0
Summary: An interactive graphical interface to make turtle programming easier & better
Keywords: turtle,turtleide,interactiveturtle
Author: Arsalan Arish
Author-email: Arsalan Arish <mail@arsalanarish.com>
License-Expression: MIT
Maintainer: Arsalan Arish
Maintainer-email: Arsalan Arish <mail@arsalanarish.com>
Requires-Python: >=3.11
Project-URL: Repository, https://github.com/arsalan-arish/turtlelab
